dmrid_lookup/__init__.py
dmrid_lookup/dmrid_lookup.py
dmrid_lookup-1.0.22.dist-info/METADATA
dmrid_lookup-1.0.22.dist-info/WHEEL
dmrid_lookup-1.0.22.dist-info/entry_points.txt
dmrid_lookup-1.0.22.dist-info/top_level.txt
dmrid_lookup-1.0.22.dist-info/RECORD
