Metadata-Version: 2.4
Name: dmrid_lookup
Version: 1.0.22
Summary: A Python package for looking up DMR IDs from radioid.net
Home-page: https://github.com/k6ef/dmrid_lookup
Author: Mark Cohen
Author-email: k6ef@k6ef.net
Classifier: Programming Language :: Python :: 3
Classifier: License :: OSI Approved :: MIT License
Classifier: Operating System :: OS Independent
Requires-Python: >=3.6
Requires-Dist: requests>=2.25.1
Requires-Dist: rich>=10.0.0
Dynamic: author
Dynamic: author-email
Dynamic: classifier
Dynamic: description
Dynamic: description-content-type
Dynamic: home-page
Dynamic: requires-dist
Dynamic: requires-python
Dynamic: summary
